pyhead_demo/__init__.py
pyhead_demo/__main__.py
pyhead_demo-0.1.0.dist-info/METADATA
pyhead_demo-0.1.0.dist-info/WHEEL
pyhead_demo-0.1.0.dist-info/entry_points.txt
pyhead_demo-0.1.0.dist-info/top_level.txt
pyhead_demo-0.1.0.dist-info/RECORD
