Metadata-Version: 2.4
Name: pyhead-demo
Version: 0.1.0
Summary: A Python implementation of the head command.
Home-page: https://github.com/anastasiatrushchak/pyhead-demo
Author: Анастасія
Author-email: trushchaknastya@gmail.com
Classifier: Programming Language :: Python :: 3
Classifier: License :: OSI Approved :: MIT License
Classifier: Operating System :: OS Independent
Requires-Python: >=3.7
Requires-Dist: click
Dynamic: author
Dynamic: author-email
Dynamic: classifier
Dynamic: description
Dynamic: description-content-type
Dynamic: home-page
Dynamic: requires-dist
Dynamic: requires-python
Dynamic: summary
